Metadata-Version: 1.0
Name: Binomial-and-Gaussian-Distribution
Version: 0.1
Summary: Binomial and Gaussian distributions
Home-page: UNKNOWN
Author: UNKNOWN
Author-email: UNKNOWN
License: UNKNOWN
Platform: UNKNOWN
